MANIFEST.in
README.rst
setup.py
pathinby/__init__.py
pathinby/pathinby.py
pathinby.egg-info/PKG-INFO
pathinby.egg-info/SOURCES.txt
pathinby.egg-info/dependency_links.txt
pathinby.egg-info/entry_points.txt
pathinby.egg-info/top_level.txt