Metadata-Version: 1.0
Name: pathinby
Version: 0.1
Summary: Generate a hierarchy of the contents of a directory, Possibly outputting to a file
Home-page: https://github.com/shockry/pathinby
Author: Shokry
Author-email: shokry92@gmail.com
License: MIT
Platform: UNKNOWN
